kerliix_oauth/__init__.py
kerliix_oauth/cache.py
kerliix_oauth/client.py
kerliix_oauth/types.py
kerliix_oauth-1.0.0.dist-info/licenses/LICENSE
kerliix_oauth-1.0.0.dist-info/METADATA
kerliix_oauth-1.0.0.dist-info/WHEEL
kerliix_oauth-1.0.0.dist-info/top_level.txt
kerliix_oauth-1.0.0.dist-info/RECORD
