Metadata-Version: 2.4
Name: kerliix-oauth
Version: 1.0.0
Summary: Kerliix OAuth 2.0 SDK for Python
Home-page: https://github.com/kerliix-corp/kerliix-oauth-python
Author: Kerliix Corporation
Author-email: dev@kerliix.com
Classifier: Programming Language :: Python :: 3
Classifier: License :: OSI Approved :: MIT License
Classifier: Operating System :: OS Independent
Requires-Python: >=3.9
License-File: LICENSE
Requires-Dist: requests>=2.28.0
Dynamic: author
Dynamic: author-email
Dynamic: classifier
Dynamic: description
Dynamic: description-content-type
Dynamic: home-page
Dynamic: license-file
Dynamic: requires-dist
Dynamic: requires-python
Dynamic: summary
